swarmauri_evaluatorpool_accessibility/AccessibilityEvaluatorPool.py
swarmauri_evaluatorpool_accessibility/AutomatedReadabilityIndexEvaluator.py
swarmauri_evaluatorpool_accessibility/ColemanLiauIndexEvaluator.py
swarmauri_evaluatorpool_accessibility/FleschKincaidGradeEvaluator.py
swarmauri_evaluatorpool_accessibility/FleschReadingEaseEvaluator.py
swarmauri_evaluatorpool_accessibility/GunningFogEvaluator.py
swarmauri_evaluatorpool_accessibility/__init__.py
swarmauri_evaluatorpool_accessibility-0.1.2.dist-info/LICENSE
swarmauri_evaluatorpool_accessibility-0.1.2.dist-info/METADATA
swarmauri_evaluatorpool_accessibility-0.1.2.dist-info/WHEEL
swarmauri_evaluatorpool_accessibility-0.1.2.dist-info/entry_points.txt
swarmauri_evaluatorpool_accessibility-0.1.2.dist-info/RECORD
