Metadata-Version: 2.3
Name: swarmauri_evaluatorpool_accessibility
Version: 0.1.2
Summary: A package providing accessibility and readability evaluators for SwarmAuri
License: Apache-2.0
Keywords: accessibility,readability,evaluator,swarmauri,flesch-kincaid,gunning-fog,coleman-liau,automated-readability-index,flesch-reading-ease,text-analysis,nlp
Author: SwarmAuri Team
Author-email: info@swarmauri.com
Requires-Python: >=3.10,<3.13
Classifier: License :: OSI Approved :: Apache Software License
Classifier: Natural Language :: English
Classifier: Programming Language :: Python :: 3.10
Classifier: Programming Language :: Python :: 3.11
Classifier: Programming Language :: Python :: 3.12
Classifier: Intended Audience :: Developers
Classifier: Topic :: Software Development :: Libraries :: Python Modules
Classifier: Topic :: Text Processing :: Linguistic
Classifier: Topic :: Software Development :: Quality Assurance
Requires-Dist: beautifulsoup4
Requires-Dist: markdown
Requires-Dist: nltk
Requires-Dist: pydantic
Requires-Dist: swarmauri_base
Requires-Dist: swarmauri_core
Requires-Dist: swarmauri_standard
